CHANGELOG.rst
MANIFEST.in
README.rst
setup.py
django_oscar_unicredit.egg-info/PKG-INFO
django_oscar_unicredit.egg-info/SOURCES.txt
django_oscar_unicredit.egg-info/dependency_links.txt
django_oscar_unicredit.egg-info/top_level.txt
unicredit/__init__.py
unicredit/admin.py
unicredit/exceptions.py
unicredit/facade.py
unicredit/models.py
unicredit/urls.py
unicredit/views.py
unicredit/migrations/0001_initial.py
unicredit/migrations/__init__.py