Metadata-Version: 1.0
Name: django-oscar-unicredit
Version: 0.1
Summary: A plugin to pay with unicredit bank
Home-page: https://github.com/marcominutoli/django-oscar-unicredit
Author: Marco Minutoli
Author-email: info@marcominutoli.it
License: BSD
Keywords: E-commerce,Django,domain-driven,Payment,Unicredit
Platform: UNKNOWN
Classifier: Environment :: Web Environment
Classifier: Framework :: Django
Classifier: Intended Audience :: Developers
Classifier: License :: OSI Approved :: BSD License
Classifier: Operating System :: Unix
Classifier: Programming Language :: Python
